MANIFEST.in
README.md
setup.py
dash_table_experiments/__init__.py
dash_table_experiments/bundle.js
dash_table_experiments/bundle.js.map
dash_table_experiments/dash_table_experiments.css
dash_table_experiments/metadata.json
dash_table_experiments/version.py
dash_table_experiments.egg-info/PKG-INFO
dash_table_experiments.egg-info/SOURCES.txt
dash_table_experiments.egg-info/dependency_links.txt
dash_table_experiments.egg-info/top_level.txt
test/test_integration.py