Metadata-Version: 1.0
Name: dash-table-experiments
Version: 0.6.0
Summary: Dash table experiments
Home-page: UNKNOWN
Author: plotly
Author-email: UNKNOWN
License: MIT
Platform: UNKNOWN
